socketbee/__init__.py
socketbee/client.py
socketbee/settings.py
socketbee-0.1.4.dist-info/LICENSE.md
socketbee-0.1.4.dist-info/METADATA
socketbee-0.1.4.dist-info/WHEEL
socketbee-0.1.4.dist-info/top_level.txt
socketbee-0.1.4.dist-info/RECORD
