Metadata-Version: 2.1
Name: socketbee
Version: 0.1.4
Summary: A Python wrapper for the SocketBee.
Author-email: "Boulama K." <boulama@otimbi.com>
Project-URL: Homepage, https://github.com/socketbee/socketbee.py
Project-URL: Bug Tracker, https://github.com/socketbee/socketbee.py/issues
Classifier: Development Status :: 2 - Pre-Alpha
Classifier: Programming Language :: Python :: 3
Classifier: License :: OSI Approved :: MIT License
Classifier: Operating System :: OS Independent
Requires-Python: >=3.7
License-File: LICENSE.md
Requires-Dist: requests
